nemo/__init__.py
nemo/__main__.py
nemo/__version__.py
nemo/analysis.py
nemo/batch.py
nemo/eom.py
nemo/omega.py
nemo/parser.py
nemo/tools.py
nemophoto-1.3.2.dist-info/licenses/LICENSE
nemophoto-1.3.2.dist-info/METADATA
nemophoto-1.3.2.dist-info/WHEEL
nemophoto-1.3.2.dist-info/entry_points.txt
nemophoto-1.3.2.dist-info/top_level.txt
nemophoto-1.3.2.dist-info/RECORD
