Metadata-Version: 2.4
Name: nemophoto
Version: 1.3.2
Summary: Absorption, fluorescence, phosphorescence spectrum simulations and ISC rate calculations.
Author-email: Leonardo Evaristo de Sousa <ledso@dtu.dk>
License-Expression: MIT
Project-URL: Homepage, https://github.com/LeonardoESousa/NEMO
Requires-Python: >=3.6
License-File: LICENSE
Requires-Dist: numpy
Requires-Dist: pandas
Requires-Dist: scipy
Requires-Dist: LeoX>=0.9.0
Dynamic: license-file
